[
  {
    "id": "Chainsaw Man",
    "name": "Chainsaw Man",
    "source_url": "https://readchainsaw-man.com/",
    "latest_chapter_text": "Chainsaw Man – Chapter 220",
    "latest_chapter_url": "https://w3.readchainsaw-man.com/manga/chainsaw-man-chapter-220/",
    "last_scraped_at": "2025-11-10T03:17:10.815076"
  },
  {
    "id": "Dandadan",
    "name": "Dandadan",
    "source_url": "https://www.dandadanchapters.com/",
    "latest_chapter_text": "Error",
    "latest_chapter_url": null,
    "last_scraped_at": "2025-11-10T03:17:11.416260"
  },
  {
    "id": "Kagurabachi",
    "name": "Kagurabachi",
    "source_url": "https://readkagura.com/",
    "latest_chapter_text": "Kagurabachi, Chapter 100",
    "latest_chapter_url": "https://readkagura.com/manga/kagurabachi-chapter-100/",
    "last_scraped_at": "2025-11-10T03:17:26.533880"
  },
  {
    "id": "Sakamoto Days",
    "name": "Sakamoto Days",
    "source_url": "https://www.sakamotodayschapters.com/",
    "latest_chapter_text": "Error",
    "latest_chapter_url": null,
    "last_scraped_at": "2025-11-10T03:17:26.752735"
  },
  {
    "id": "One Punch Man",
    "name": "One Punch Man",
    "source_url": "https://readonepunch-man.com/",
    "latest_chapter_text": "One Punch Man Chapter 211",
    "latest_chapter_url": "https://readonepunch-man.com/one-punch-man-chapter-211/",
    "last_scraped_at": "2025-11-10T03:17:41.871818"
  },
  {
    "id": "Eleceed",
    "name": "Eleceed",
    "source_url": "https://www.toongod.org/webtoon/eleceed-manhwa/",
    "latest_chapter_text": "Error",
    "latest_chapter_url": null,
    "last_scraped_at": "2025-11-10T03:17:43.083202"
  }
]